annexlang/__init__.py
annexlang/components.py
annexlang/language.py
annexlang/styles.py
annexlang/tikzpicture.py
annexlang-0.3.data/scripts/annex-convert
annexlang-0.3.dist-info/DESCRIPTION.rst
annexlang-0.3.dist-info/METADATA
annexlang-0.3.dist-info/RECORD
annexlang-0.3.dist-info/WHEEL
annexlang-0.3.dist-info/metadata.json
annexlang-0.3.dist-info/top_level.txt
