Metadata-Version: 2.0
Name: annexlang
Version: 0.3
Summary: A description language for drawing communication protocols in TeX documents.
Home-page: http://github.com/webhamster/annexlang
Author: Daniel Fett
Author-email: github@danielfett.de
License: MIT
Platform: UNKNOWN
Classifier: Programming Language :: Python :: 3
Classifier: Programming Language :: Python :: 3.5
Classifier: Programming Language :: Python :: 3.6
Requires-Dist: pyyaml
